django_wireguard/__init__.py
django_wireguard/admin.py
django_wireguard/apps.py
django_wireguard/forms.py
django_wireguard/models.py
django_wireguard/settings.py
django_wireguard/signals.py
django_wireguard/sync_wg.py
django_wireguard/utils.py
django_wireguard/validators.py
django_wireguard/wireguard.py
django_wireguard/management/__init__.py
django_wireguard/management/commands/__init__.py
django_wireguard/management/commands/clear_private_keys.py
django_wireguard/management/commands/create_peer.py
django_wireguard/management/commands/delete_peers.py
django_wireguard/management/commands/setup_interface.py
django_wireguard/migrations/0001_initial.py
django_wireguard/migrations/__init__.py
django_wireguard/static/js/inject_qrcode.js
django_wireguard/static/js/qrcode.min.js
django_wireguard/templates/django_wireguard/wireguardpeer_change_form.html
django_wireguard/templates/django_wireguard/wireguardpeer_inspect.html
django_wireguard/templatetags/__init__.py
django_wireguard/templatetags/django_wireguard_filters.py
django_wireguard/tests/__init__.py
django_wireguard/tests/helpers.py
django_wireguard/tests/test_package.py
django_wireguard/tests/testapp/__init__.py
django_wireguard/tests/testapp/settings.py
django_wireguard/tests/testapp/urls.py
django_wireguard/wagtail/__init__.py
django_wireguard/wagtail/admin.py
django_wireguard-0.2.0.dist-info/LICENCE
django_wireguard-0.2.0.dist-info/METADATA
django_wireguard-0.2.0.dist-info/WHEEL
django_wireguard-0.2.0.dist-info/top_level.txt
django_wireguard-0.2.0.dist-info/RECORD
