Metadata-Version: 2.1
Name: django-wireguard
Version: 0.2.0
Summary: A Django app for managing WireGuard Interfaces.
Home-page: https://gitlab.com/thatsed/django-wireguard
Author: Alessandro Romani
Author-email: romani.ae98@gmail.com
License: MIT
Platform: UNKNOWN
Classifier: Environment :: Web Environment
Classifier: Framework :: Django
Classifier: Framework :: Django :: 3.1
Classifier: Intended Audience :: Developers
Classifier: License :: OSI Approved :: MIT License
Classifier: Operating System :: POSIX :: Linux
Classifier: Programming Language :: Python
Classifier: Programming Language :: Python :: 3
Classifier: Programming Language :: Python :: 3 :: Only
Classifier: Programming Language :: Python :: 3.6
Classifier: Programming Language :: Python :: 3.7
Classifier: Programming Language :: Python :: 3.8
Classifier: Topic :: Internet :: WWW/HTTP
Classifier: Topic :: Internet :: WWW/HTTP :: Dynamic Content
Requires-Python: >=3.6
Requires-Dist: Django (>=2.2)
Requires-Dist: pyroute2 (>=0.5.14)
Requires-Dist: cryptography (>=3.2.1)
